{
  "demo_summary": {
    "total_demos": 5,
    "successful_demos": 5,
    "failed_demos": 0,
    "success_rate": 1.0,
    "overall_automation_level": 66.66666666666667,
    "execution_time": 3.840479
  },
  "demo_details": [
    {
      "demo_name": "Configuration Management",
      "status": "success",
      "overall_health": "healthy",
      "services_configured": 4,
      "degraded_features": 4,
      "fallback_storage_created": true
    },
    {
      "demo_name": "Advanced Algorithm Templates",
      "status": "success",
      "templates_available": 3,
      "test_algorithms_created": 0,
      "validation_tests_passed": 0,
      "total_validation_tests": 0,
      "template_categories": [
        "optimization",
        "anomaly_detection"
      ],
      "quantum_enhanced_count": 3
    },
    {
      "demo_name": "Advanced Automation Workflows",
      "status": "success",
      "workflows_created": 3,
      "workflows_executed": 3,
      "successful_workflows": 1,
      "average_automation_level": 100.0,
      "workflow_details": {
        "decision": {
          "success": false,
          "automation_level": 0.0,
          "steps_completed": 0
        },
        "algorithm": {
          "success": false,
          "automation_level": 0.0,
          "steps_completed": 0
        },
        "deployment": {
          "success": true,
          "automation_level": 100.0,
          "steps_completed": 6
        }
      }
    },
    {
      "demo_name": "Workflow Orchestration",
      "status": "success",
      "orchestrator_created": true,
      "workflows_registered": 3,
      "sequence_executed": true,
      "sequence_success": false,
      "overall_automation": 33.333333333333336,
      "orchestrator_summary": {
        "total_sequences": 1,
        "total_workflows_executed": 3,
        "successful_sequences": 0,
        "success_rate": 0.0,
        "average_automation_level": 33.333333333333336,
        "last_orchestration": "2025-08-28 06:06:11.334259"
      }
    },
    {
      "demo_name": "Performance & Integration",
      "status": "success",
      "total_demo_time": 3.839616,
      "demo_success_rate": 1.0,
      "overall_automation_level": 66.66666666666667,
      "integration_status": {
        "configuration_manager": true,
        "algorithm_templates": 3,
        "workflow_orchestrator": true,
        "all_components_available": true
      },
      "performance_metrics": {
        "total_demos": 4,
        "successful_demos": 4,
        "failed_demos": 0
      }
    }
  ],
  "timestamp": "2025-08-28T06:06:11.335981",
  "platform_version": "2.0.0",
  "capabilities_demonstrated": [
    "Advanced Configuration Management",
    "World-Class Algorithm Templates",
    "Advanced Automation Workflows",
    "Workflow Orchestration",
    "Performance Integration"
  ]
}